Metadata-Version: 1.1
Name: gideon
Version: 0.0.2
Summary: simple gideon library for python3 and python2
Home-page: UNKNOWN
Author: Overnice.exe
Author-email: silkepilon2009@gmail.com
License: MIT
Platform: UNKNOWN
Classifier: Development Status :: 5 - Production/Stable
Classifier: Operating System :: OS Independent
Classifier: License :: OSI Approved :: MIT License
Classifier: Programming Language :: Python :: 3
